{
    "version": "https://jsonfeed.org/version/1",
    "title": "Thao Le Blog",
    "description": "",
    "home_page_url": "https://thaole.me",
    "feed_url": "https://thaole.me/feed.json",
    "user_comment": "",
    "author": {
        "name": "Thao Le"
    },
    "items": [
        {
            "id": "https://thaole.me/tu-lam-blog-ca-nhan-voi-publii.html",
            "url": "https://thaole.me/tu-lam-blog-ca-nhan-voi-publii.html",
            "title": "Tự làm blog cá nhân với Publii",
            "image": "https://thaole.me/media/posts/8/",
            "author": {
                "name": "Thao Le"
            },
            "tags": [
            ],
            "date_published": "2019-01-10T08:37:56+07:00",
            "date_modified": "2019-01-10T08:40:23+07:00"
        },
        {
            "id": "https://thaole.me/phat-trien-va-trien-khai-ung-dung-web-mien-phi-su-dung-nuxtjs-va-surgesh.html",
            "url": "https://thaole.me/phat-trien-va-trien-khai-ung-dung-web-mien-phi-su-dung-nuxtjs-va-surgesh.html",
            "title": "Phát triển và triển khai ứng dụng web miễn phí sử dụng Nuxt.js và surge.sh",
            "image": "https://thaole.me/media/posts/7/",
            "author": {
                "name": "Thao Le"
            },
            "tags": [
                   "phát triển web",
                   "nodejs"
            ],
            "date_published": "2019-01-10T08:37:03+07:00",
            "date_modified": "2019-01-10T08:37:03+07:00"
        },
        {
            "id": "https://thaole.me/bien-dich-va-cai-dat-linux-kernel-module-cho-ic-giao-tiep-usb-max3421e.html",
            "url": "https://thaole.me/bien-dich-va-cai-dat-linux-kernel-module-cho-ic-giao-tiep-usb-max3421e.html",
            "title": "Biên dịch và cài đặt Linux kernel module cho IC giao tiếp USB MAX3421E",
            "image": "https://thaole.me/media/posts/6/",
            "author": {
                "name": "Thao Le"
            },
            "tags": [
                   "linux"
            ],
            "date_published": "2019-01-10T08:25:43+07:00",
            "date_modified": "2019-01-10T08:25:48+07:00"
        },
        {
            "id": "https://thaole.me/vai-huong-dan-ve-lap-trinh-c-tren-linux.html",
            "url": "https://thaole.me/vai-huong-dan-ve-lap-trinh-c-tren-linux.html",
            "title": "Vài hướng dẫn về lập trình C++ trên Linux",
            "image": "https://thaole.me/media/posts/5/",
            "author": {
                "name": "Thao Le"
            },
            "tags": [
                   "cpp"
            ],
            "date_published": "2019-01-10T08:22:42+07:00",
            "date_modified": "2019-01-10T08:25:13+07:00"
        },
        {
            "id": "https://thaole.me/thiet-lap-moi-truong-lap-trinh-nhung-voi-qtcreator.html",
            "url": "https://thaole.me/thiet-lap-moi-truong-lap-trinh-nhung-voi-qtcreator.html",
            "title": "Thiết lập môi trường lập trình nhúng với QtCreator",
            "summary": "qtcreator arm-none-eabi",
            "content_html": "<p>qtcreator</p>\n<p>arm-none-eabi</p>",
            "image": "https://thaole.me/media/posts/4/",
            "author": {
                "name": "Thao Le"
            },
            "tags": [
                   "cpp"
            ],
            "date_published": "2019-01-10T08:20:33+07:00",
            "date_modified": "2019-01-10T08:20:39+07:00"
        },
        {
            "id": "https://thaole.me/phat-trien-ung-dung-web-nhanh-chong-voi-laravel-angular-swagger.html",
            "url": "https://thaole.me/phat-trien-ung-dung-web-nhanh-chong-voi-laravel-angular-swagger.html",
            "title": "Phát triển ứng dụng web nhanh chóng với Laravel, Angular và Swagger",
            "summary": "Laravel Angular Swagger ",
            "content_html": "<p>Laravel</p>\n<p>Angular</p>\n<p>Swagger</p>\n<p> </p>",
            "image": "https://thaole.me/media/posts/3/",
            "author": {
                "name": "Thao Le"
            },
            "tags": [
                   "phát triển web"
            ],
            "date_published": "2019-01-10T06:45:48+07:00",
            "date_modified": "2019-01-10T07:15:09+07:00"
        },
        {
            "id": "https://thaole.me/bien-dich-linux-nhung-cho-kit-phat-trien-violino.html",
            "url": "https://thaole.me/bien-dich-linux-nhung-cho-kit-phat-trien-violino.html",
            "title": "Biên dịch Linux nhúng cho kit phát triển Violino",
            "summary": "https://github.com/thiennhan92/violino https://github.com/SongPhi/violino-vagrant ",
            "content_html": "<p><a href=\"https://github.com/thiennhan92/violino\">https://github.com/thiennhan92/violino</a></p>\n<p><a href=\"https://github.com/SongPhi/violino-vagrant\">https://github.com/SongPhi/violino-vagrant</a></p>\n<p><img class=\"post__image\" src=\"https://thaole.me/media/posts/2/top.jpg\" alt=\"\" width=\"2048\" height=\"1152\"></p>\n<p> </p>\n<p><img class=\"post__image\" src=\"https://thaole.me/media/posts/2/violino-linux-with-lcd.jpg\" alt=\"\" width=\"1152\" height=\"2048\"></p>",
            "image": "https://thaole.me/media/posts/2/violino-first-boot.png",
            "author": {
                "name": "Thao Le"
            },
            "tags": [
                   "linux"
            ],
            "date_published": "2019-01-10T06:42:55+07:00",
            "date_modified": "2019-01-10T07:30:04+07:00"
        },
        {
            "id": "https://thaole.me/xay-dung-chatbot-voi-microsoft-botframework-bang-nodejs-and-trien-khai-len-heroku.html",
            "url": "https://thaole.me/xay-dung-chatbot-voi-microsoft-botframework-bang-nodejs-and-trien-khai-len-heroku.html",
            "title": "Xây dựng chatbot với Microsoft Botframework bằng NodeJS &amp; triển khai lên Heroku",
            "summary": "https://github.com/spthaolt/lukebot https://lukechatbot.herokuapp.com Cài đặt công cụ cần thiết Thiết lập Heroku Azure NodeJS",
            "content_html": "<p><a href=\"https://github.com/spthaolt/lukebot\">https://github.com/spthaolt/lukebot</a></p>\n<p><a href=\"https://lukechatbot.herokuapp.com\">https://lukechatbot.herokuapp.com</a></p>\n<p>Cài đặt công cụ cần thiết</p>\n<p>Thiết lập</p>\n<p>Heroku</p>\n<p>Azure</p>\n<p>NodeJS</p>",
            "image": "https://thaole.me/media/posts/1/",
            "author": {
                "name": "Thao Le"
            },
            "tags": [
                   "nodejs"
            ],
            "date_published": "2019-01-10T06:36:17+07:00",
            "date_modified": "2019-01-10T06:44:49+07:00"
        }
    ]
}
